Workbook

Sheet Pricing
A1: ADT TOOL · EQUIPMENT PRICING
A3: Blue cells are inputs — part cost, labor, and retail. Total cost, margin, and margin % calculate. These are the same numbers the ADT Tool loads.
A4: Retail marked "derived" has no price on the ADT Primary Command sheet; the tool prices it at cost + 30%, rounded to the dollar.
A6: Category | B6: Item | C6: Part # | D6: Part Cost | E6: Labor | F6: Total Cost | G6: Retail | H6: Margin $ | I6: Margin % | J6: Retail source
A7: Panels | B7: 5in Screen | C7: ADT5AIO-4 + ADTLTE-V3 | D7: 227.65 | E7: 149 | F7: =D7+E7 -> 376.65 | G7: 450 | H7: =G7-F7 -> 73.35 | I7: =IF(G7=0,"",H7/G7) -> 0.163 | J7: ADT sheet
A8: Panels | B8: 7in Screen | C8: ADT7AIO-4 + ADTLTE-V3 | D8: 267.98 | E8: 149 | F8: =D8+E8 -> 416.98 | G8: 550 | H8: =G8-F8 -> 133.02 | I8: =IF(G8=0,"",H8/G8) -> 0.24185455 | J8: ADT sheet
A9: Panels | B9: Hybrid Panel | C9: ADTHYBWL-2 | D9: 109.25 | E9: 75 | F9: =D9+E9 -> 184.25 | G9: 240 | H9: =G9-F9 -> 55.75 | I9: =IF(G9=0,"",H9/G9) -> 0.23229167 | J9: derived · cost +30%
A10: Panels | B10: AT&T Radio | C10: ADTLTE-A3 | D10: 61.53 | E10: 0 | F10: =D10+E10 -> 61.53 | G10: 80 | H10: =G10-F10 -> 18.47 | I10: =IF(G10=0,"",H10/G10) -> 0.230875 | J10: derived · cost +30%
A11: Panels | B11: 8-Zone Converter | C11: SIXC2WA | D11: 51.68 | E11: 0 | F11: =D11+E11 -> 51.68 | G11: 99 | H11: =G11-F11 -> 47.32 | I11: =IF(G11=0,"",H11/G11) -> 0.4779798 | J11: ADT sheet
A12: Panels | B12: Wireless Converter | C12: ADTCONVERT | D12: 49.22 | E12: 0 | F12: =D12+E12 -> 49.22 | G12: 99 | H12: =G12-F12 -> 49.78 | I12: =IF(G12=0,"",H12/G12) -> 0.50282828 | J12: ADT sheet
A13: Panels | B13: Wi-Fi Extender | C13: RE305 | D13: 53 | E13: 0 | F13: =D13+E13 -> 53 | G13: 199 | H13: =G13-F13 -> 146 | I13: =IF(G13=0,"",H13/G13) -> 0.73366834 | J13: ADT sheet
A14: Sensors | B14: Door Sensor | C14: SIXCTA | D14: 12.64 | E14: 15 | F14: =D14+E14 -> 27.64 | G14: 159 | H14: =G14-F14 -> 131.36 | I14: =IF(G14=0,"",H14/G14) -> 0.82616352 | J14: ADT sheet
A15: Sensors | B15: Motion | C15: SIXPIRA | D15: 31.6 | E15: 15 | F15: =D15+E15 -> 46.6 | G15: 299 | H15: =G15-F15 -> 252.4 | I15: =IF(G15=0,"",H15/G15) -> 0.84414716 | J15: ADT sheet
A16: Sensors | B16: Glassbreak | C16: SIXGBA | D16: 45.5 | E16: 15 | F16: =D16+E16 -> 60.5 | G16: 299 | H16: =G16-F16 -> 238.5 | I16: =IF(G16=0,"",H16/G16) -> 0.79765886 | J16: ADT sheet
A17: Sensors | B17: Shock Sensor | C17: SIXSHOCK2A | D17: 22.74 | E17: 15 | F17: =D17+E17 -> 37.74 | G17: 199 | H17: =G17-F17 -> 161.26 | I17: =IF(G17=0,"",H17/G17) -> 0.81035176 | J17: ADT sheet
A18: Life Safety | B18: Smoke | C18: SIXSMOKEA | D18: 45.5 | E18: 15 | F18: =D18+E18 -> 60.5 | G18: 299 | H18: =G18-F18 -> 238.5 | I18: =IF(G18=0,"",H18/G18) -> 0.79765886 | J18: ADT sheet
... A47: Misc | B47: Command Labor | C47: — | D47: 0 | E47: 25 | F47: =D47+E47 -> 25 | G47: 33 | H47: =G47-F47 -> 8 | I47: =IF(G47=0,"",H47/G47) -> 0.24242424 | J47: derived · cost +30%
A48: TOTALS | D48: =SUM(D7:D47) -> 2953.36 | E48: =SUM(E7:E47) -> 898 | F48: =SUM(F7:F47) -> 3851.36 | G48: =SUM(G7:G47) -> 9714 | H48: =SUM(H7:H47) -> 5862.64 | I48: =IF(G48=0,"",H48/G48) -> 0.60352481

Sheet By Category
A1: COST & MARGIN BY CATEGORY
A4: Category | B4: Items | C4: Total Cost | D4: Total Retail | E4: Margin
A5: Panels | B5: =COUNTIF(Pricing!$A$7:$A$47,$A5) -> 7 | C5: =SUMIF(Pricing!$A$7:$A$47,$A5,Pricing!$F$7:$F$47) -> 1193.31 | D5: =SUMIF(Pricing!$A$7:$A$47,$A5,Pricing!$G$7:$G$47) -> 1717 | E5: =SUMIF(Pricing!$A$7:$A$47,$A5,Pricing!$H$7:$H$47) -> 523.69
A6: Sensors | B6: =COUNTIF(Pricing!$A$7:$A$47,$A6) -> 4 | C6: =SUMIF(Pricing!$A$7:$A$47,$A6,Pricing!$F$7:$F$47) -> 172.48 | D6: =SUMIF(Pricing!$A$7:$A$47,$A6,Pricing!$G$7:$G$47) -> 956 | E6: =SUMIF(Pricing!$A$7:$A$47,$A6,Pricing!$H$7:$H$47) -> 783.52
A7: Life Safety | B7: =COUNTIF(Pricing!$A$7:$A$47,$A7) -> 4 | C7: =SUMIF(Pricing!$A$7:$A$47,$A7,Pricing!$F$7:$F$47) -> 301.54 | D7: =SUMIF(Pricing!$A$7:$A$47,$A7,Pricing!$G$7:$G$47) -> 1196 | E7: =SUMIF(Pricing!$A$7:$A$47,$A7,Pricing!$H$7:$H$47) -> 894.46
A8: Keypads | B8: =COUNTIF(Pricing!$A$7:$A$47,$A8) -> 7 | C8: =SUMIF(Pricing!$A$7:$A$47,$A8,Pricing!$F$7:$F$47) -> 374.73 | D8: =SUMIF(Pricing!$A$7:$A$47,$A8,Pricing!$G$7:$G$47) -> 920 | E8: =SUMIF(Pricing!$A$7:$A$47,$A8,Pricing!$H$7:$H$47) -> 545.27
A9: Cameras | B9: =COUNTIF(Pricing!$A$7:$A$47,$A9) -> 6 | C9: =SUMIF(Pricing!$A$7:$A$47,$A9,Pricing!$F$7:$F$47) -> 891.78 | D9: =SUMIF(Pricing!$A$7:$A$47,$A9,Pricing!$G$7:$G$47) -> 2094 | E9: =SUMIF(Pricing!$A$7:$A$47,$A9,Pricing!$H$7:$H$47) -> 1202.22
A10: Smart Home | B10: =COUNTIF(Pricing!$A$7:$A$47,$A10) -> 9 | C10: =SUMIF(Pricing!$A$7:$A$47,$A10,Pricing!$F$7:$F$47) -> 710.93 | D10: =SUMIF(Pricing!$A$7:$A$47,$A10,Pricing!$G$7:$G$47) -> 2131 | E10: =SUMIF(Pricing!$A$7:$A$47,$A10,Pricing!$H$7:$H$47) -> 1420.07
A11: Misc | B11: =COUNTIF(Pricing!$A$7:$A$47,$A11) -> 4 | C11: =SUMIF(Pricing!$A$7:$A$47,$A11,Pricing!$F$7:$F$47) -> 206.59 | D11: =SUMIF(Pricing!$A$7:$A$47,$A11,Pricing!$G$7:$G$47) -> 700 | E11: =SUMIF(Pricing!$A$7:$A$47,$A11,Pricing!$H$7:$H$47) -> 493.41
A12: ALL CATEGORIES | B12: =SUM(B5:B11) -> 41 | C12: =SUM(C5:C11) -> 3851.36 | D12: =SUM(D5:D11) -> 9714 | E12: =SUM(E5:E11) -> 5862.64

Sheet Model
A1: FUNDING MODEL · REFERENCE
A4: CREDIT TIERS
A5: Tier | B5: Score | C5: Multiple | D5: Attrition
A6: A+ | B6: 795+ | C6: 34 | D6: 0.15
A7: A | B7: 760-794 | C7: 33 | D7: 0.15
A8: B | B8: 705-759 | C8: 32 | D8: 0.15
A9: B- | B9: 665-704 | C9: 29 | D9: 0.15
A10: D | B10: 640-664 | C10: 27 | D10: 0.15
A11: E | B11: 600-639 | C11: 26 | D11: 0.15
A12: Commercial | B12: — | C12: 26 | D12: 0.15
A14: SERVICE PACKAGES
A15: Package | B15: Cost of service | C15: Standard rate | D15: Fundable band
A16: Basic w/o app control | B16: -3.5 | C16: 51.99 | D16: $42.99 – $53.99
A17: Basic w/ app control | B17: -3.5 | C17: 53.99 | D17: $42.99 – $53.99
A18: Basic + smart/video | B18: -6.5 | C18: 61.99 | D18: $51.99 – $74.99
A19: Basic + smart/video + Nest Aware Plus | B19: -8 | C19: 81.99 | D19: $58.99 – $81.99
A22: FEES
A23: Activation (customer pays) | B23: 99
A24: Admin fee (deducted) | B24: 199
A25: Merchant fee | B25: 0
A26: ADC fee | B26: 0
A29: FORMULAS
A30: Gross funding = (MMR + cost of service) × tier multiple
A31: Budget = gross funding + activation
A32: Cost of goods = part cost (new units only) + labor (new and existing)
A33: Commission at cost = budget − cost of goods − admin − attrition − merchant − ADC + custom margin
A34: Commission (this deal) = commission at cost + (equipment retail − credit given)
A35: Commission at full retail = commission at cost + equipment retail
A36: Customer pays = activation + equipment retail − credit given
A37: Equipment margin = equipment retail − cost of goods
A38: Attrition reserve = gross funding × tier attrition %, held back and released per the funding agreement
